tcra/__init__.py
tcra/fragility/Recovery.py
tcra/fragility/__init__.py
tcra/fragility/damageanalysis.py
tcra/fragility/fragility_curves.py
tcra/fragility/fragility_curves_epn.py
tcra/fragility/fragility_rehab.py
tcra/fragility/hurricane.py
tcra/fragility/interactive.py
tcra/fragility/montecarlosimulation.py
tcra/fragility/plot.py
tcra/simulation/Recovery.py
tcra/simulation/__init__.py
tcra/simulation/damageanalysis.py
tcra/simulation/fragility_rehab.py
tcra/simulation/hurricane.py
tcra/simulation/interactive.py
tcra/simulation/montecarlosimulation.py
tcra/simulation/plot.py
tcra-1.1.3.dist-info/LICENSE.md
tcra-1.1.3.dist-info/METADATA
tcra-1.1.3.dist-info/WHEEL
tcra-1.1.3.dist-info/top_level.txt
tcra-1.1.3.dist-info/RECORD
