Metadata-Version: 2.1
Name: tcra
Version: 1.1.3
Summary: A Python package for estimating cyclone hazard parameters and calculating wind speeds at structure sites.
Home-page: https://github.com/rxm562/TCRA.git
Author: Ram Krishna Mazumder
Author-email: rkmazumder@gmail.com
License: MIT
Classifier: Programming Language :: Python :: 3
Classifier: License :: OSI Approved :: MIT License
Classifier: Operating System :: OS Independent
Requires-Python: >=3.6
License-File: LICENSE.md
Requires-Dist: numpy <3.0.0,>=1.21.0
Requires-Dist: pandas >=1.3.0
Requires-Dist: matplotlib >=3.4.0
Requires-Dist: scipy >=1.6.0
Requires-Dist: folium >=0.12.0
